py_cdk_utils/__init__.py
py_cdk_utils/environments.py
py_cdk_utils-1.0.0.dist-info/LICENSE.md
py_cdk_utils-1.0.0.dist-info/WHEEL
py_cdk_utils-1.0.0.dist-info/METADATA
py_cdk_utils-1.0.0.dist-info/RECORD
