Metadata-Version: 2.1
Name: py-cdk-utils
Version: 1.0.0
Summary: Utilities to assist with building Python-based applications in AWS-CDK
License: MIT
Author: Greg Farrow
Author-email: greg.farrow1@gmail.com
Requires-Python: >=3.8,<4.0
Classifier: License :: OSI Approved :: MIT License
Classifier: Programming Language :: Python :: 3
Classifier: Programming Language :: Python :: 3.8
Classifier: Programming Language :: Python :: 3.9
